LICENSE
MANIFEST.in
README.md
setup.py
./requirements.txt
kot_auth/__init__.py
kot_auth/kot_auth.py
kot_auth.egg-info/PKG-INFO
kot_auth.egg-info/SOURCES.txt
kot_auth.egg-info/dependency_links.txt
kot_auth.egg-info/not-zip-safe
kot_auth.egg-info/requires.txt
kot_auth.egg-info/top_level.txt