Metadata-Version: 2.1
Name: kot-auth
Version: 0.1.0
Summary: The cloud authentication save system for your python applications !
Home-page: https://github.com/KOT-database/KOT-Auth
Author: Onur Atakan ULUSOY
Author-email: atadogan06@gmail.com
License: MIT
Platform: UNKNOWN
Requires-Python: >= 3
